{
  "typeName": "AWS::EMR::InstanceGroupConfig",
  "description": "Resource Type definition for AWS::EMR::InstanceGroupConfig",
  "additionalProperties": false,
  "properties": {
    "JobFlowId": {
      "type": "string"
    },
    "AutoScalingPolicy": {
      "$ref": "#/definitions/AutoScalingPolicy"
    },
    "BidPrice": {
      "type": "string"
    },
    "InstanceCount": {
      "type": "integer"
    },
    "EbsConfiguration": {
      "$ref": "#/definitions/EbsConfiguration"
    },
    "InstanceRole": {
      "type": "string"
    },
    "CustomAmiId": {
      "type": "string"
    },
    "InstanceGroupId": {
      "type": "string"
    },
    "Configurations": {
      "type": "array",
      "items": {
        "$ref": "#/definitions/AppConfiguration"
      }
    },
    "InstanceType": {
      "type": "string"
    },
    "Market": {
      "type": "string"
    },
    "Name": {
      "type": "string"
    }
  },
  "definitions": {
    "AutoScalingPolicy": {
      "type": "object",
      "additionalProperties": false,
      "properties": {
        "Rules": {
          "type": "array",
          "items": {
            "$ref": "#/definitions/ScalingRule"
          }
        },
        "Constraints": {
          "$ref": "#/definitions/ScalingConstraints"
        }
      },
      "required": [
        "Constraints",
        "Rules"
      ]
    },
    "VolumeSpecification": {
      "type": "object",
      "additionalProperties": false,
      "properties": {
        "SizeInGB": {
          "type": "integer"
        },
        "Throughput": {
          "type": "integer"
        },
        "VolumeType": {
          "type": "string"
        },
        "Iops": {
          "type": "integer"
        }
      },
      "required": [
        "SizeInGB",
        "VolumeType"
      ]
    },
    "CloudWatchAlarmDefinition": {
      "type": "object",
      "additionalProperties": false,
      "properties": {
        "MetricName": {
          "type": "string"
        },
        "ComparisonOperator": {
          "type": "string"
        },
        "Statistic": {
          "type": "string"
        },
        "Dimensions": {
          "type": "array",
          "items": {
            "$ref": "#/definitions/MetricDimension"
          }
        },
        "Period": {
          "type": "integer"
        },
        "EvaluationPeriods": {
          "type": "integer"
        },
        "Unit": {
          "type": "string"
        },
        "Namespace": {
          "type": "string"
        },
        "Threshold": {
          "type": "number"
        }
      },
      "required": [
        "MetricName",
        "ComparisonOperator",
        "Period",
        "Threshold"
      ]
    },
    "EbsConfiguration": {
      "type": "object",
      "additionalProperties": false,
      "properties": {
        "EbsBlockDeviceConfigs": {
          "type": "array",
          "uniqueItems": false,
          "insertionOrder": false,
          "items": {
            "$ref": "#/definitions/EbsBlockDeviceConfig"
          }
        },
        "EbsOptimized": {
          "type": "boolean"
        }
      }
    },
    "AppConfiguration": {
      "type": "object",
      "additionalProperties": false,
      "properties": {
        "ConfigurationProperties": {
          "type": "object",
          "patternProperties": {
            "": {
              "type": "string"
            }
          },
          "additionalProperties": false
        },
        "Configurations": {
          "type": "array",
          "items": {
            "$ref": "#/definitions/AppConfiguration"
          }
        },
        "Classification": {
          "type": "string"
        }
      }
    },
    "ScalingAction": {
      "type": "object",
      "additionalProperties": false,
      "properties": {
        "Market": {
          "type": "string"
        },
        "SimpleScalingPolicyConfiguration": {
          "$ref": "#/definitions/SimpleScalingPolicyConfiguration"
        }
      },
      "required": [
        "SimpleScalingPolicyConfiguration"
      ]
    },
    "SimpleScalingPolicyConfiguration": {
      "type": "object",
      "additionalProperties": false,
      "properties": {
        "ScalingAdjustment": {
          "type": "integer"
        },
        "CoolDown": {
          "type": "integer"
        },
        "AdjustmentType": {
          "type": "string"
        }
      },
      "required": [
        "ScalingAdjustment"
      ]
    },
    "ScalingConstraints": {
      "type": "object",
      "additionalProperties": false,
      "properties": {
        "MinCapacity": {
          "type": "integer"
        },
        "MaxCapacity": {
          "type": "integer"
        }
      },
      "required": [
        "MinCapacity",
        "MaxCapacity"
      ]
    },
    "EbsBlockDeviceConfig": {
      "type": "object",
      "additionalProperties": false,
      "properties": {
        "VolumeSpecification": {
          "$ref": "#/definitions/VolumeSpecification"
        },
        "VolumesPerInstance": {
          "type": "integer",
          "description": "Use of this property can confuse CloudFormation drift detection. The EbsBlockDeviceConfigs read from the system may return a list with one entry per volume, replacing any entry specified in the template with a VolumesPerInstance greater than one by that many entries containing only the VolumeSpecification. Thus to avoid false drift detection, it is recommended to supply repeated entries in EbsBlockDeviceConfigs for any VolumeSpecification which is intended to be repeated and not to use this property.\n"
        }
      },
      "required": [
        "VolumeSpecification"
      ]
    },
    "ScalingTrigger": {
      "type": "object",
      "additionalProperties": false,
      "properties": {
        "CloudWatchAlarmDefinition": {
          "$ref": "#/definitions/CloudWatchAlarmDefinition"
        }
      },
      "required": [
        "CloudWatchAlarmDefinition"
      ]
    },
    "ScalingRule": {
      "type": "object",
      "additionalProperties": false,
      "properties": {
        "Action": {
          "$ref": "#/definitions/ScalingAction"
        },
        "Description": {
          "type": "string"
        },
        "Trigger": {
          "$ref": "#/definitions/ScalingTrigger"
        },
        "Name": {
          "type": "string"
        }
      },
      "required": [
        "Action",
        "Trigger",
        "Name"
      ]
    },
    "MetricDimension": {
      "type": "object",
      "additionalProperties": false,
      "properties": {
        "Value": {
          "type": "string"
        },
        "Key": {
          "type": "string"
        }
      },
      "required": [
        "Value",
        "Key"
      ]
    }
  },
  "required": [
    "JobFlowId",
    "InstanceCount",
    "InstanceRole",
    "InstanceType"
  ],
  "createOnlyProperties": [
    "/properties/InstanceRole",
    "/properties/JobFlowId",
    "/properties/Name",
    "/properties/InstanceType",
    "/properties/CustomAmiId",
    "/properties/Configurations",
    "/properties/EbsConfiguration",
    "/properties/Market",
    "/properties/BidPrice"
  ],
  "primaryIdentifier": [
    "/properties/InstanceGroupId",
    "/properties/JobFlowId"
  ],
  "readOnlyProperties": [
    "/properties/InstanceGroupId"
  ],
  "writeOnlyProperties": [
    "/properties/EbsConfiguration/EbsBlockDeviceConfigs/*/VolumesPerInstance"
  ],
  "tagging": {
    "taggable": false
  },
  "handlers": {
    "create": {
      "permissions": [
        "elasticmapreduce:AddInstanceGroups",
        "elasticmapreduce:ListInstanceGroups",
        "elasticmapreduce:DescribeCluster"
      ]
    },
    "read": {
      "permissions": [
        "elasticmapreduce:ListInstanceGroups",
        "elasticmapreduce:ListClusters"
      ]
    },
    "update": {
      "permissions": [
        "elasticmapreduce:ModifyInstanceGroups",
        "elasticmapreduce:PutAutoScalingPolicy",
        "elasticmapreduce:RemoveAutoScalingPolicy",
        "elasticmapreduce:ListInstanceGroups",
        "elasticmapreduce:DescribeCluster"
      ]
    },
    "delete": {
      "permissions": [
        "elasticmapreduce:ModifyInstanceGroups",
        "elasticmapreduce:RemoveAutoScalingPolicy",
        "elasticmapreduce:ListInstanceGroups",
        "elasticmapreduce:DescribeCluster"
      ]
    },
    "list": {
      "permissions": [
        "elasticmapreduce:ListInstanceGroups"
      ],
      "handlerSchema": {
        "properties": {
          "JobFlowId": {
            "type": "string"
          }
        },
        "required": [
          "JobFlowId"
        ]
      }
    }
  }
}
